yacedar-0.1.6.dist-info/METADATA
yacedar-0.1.6.dist-info/WHEEL
yacedar-0.1.6.dist-info/license_files/LICENSE
yacedar/__init__.py
yacedar/__init__.pyi
yacedar/py.typed
yacedar/yacedar.cpython-312-aarch64-linux-gnu.so
yacedar-0.1.6.dist-info/RECORD
